model_history/__init__.py
model_history/admin.py
model_history/apps.py
model_history/exceptions.py
model_history/fields.py
model_history/models.py
model_history/version.py
model_history/locale/en/LC_MESSAGES/django.mo
model_history/locale/en/LC_MESSAGES/django.po
model_history/locale/it/LC_MESSAGES/django.mo
model_history/locale/it/LC_MESSAGES/django.po
model_history/migrations/0001_initial.py
model_history/migrations/__init__.py
django_model_history_log-0.2.1.dist-info/AUTHORS
django_model_history_log-0.2.1.dist-info/COPYING
django_model_history_log-0.2.1.dist-info/METADATA
django_model_history_log-0.2.1.dist-info/WHEEL
django_model_history_log-0.2.1.dist-info/top_level.txt
django_model_history_log-0.2.1.dist-info/RECORD
