Metadata-Version: 2.1
Name: django-model-history-log
Version: 0.2.1
Summary: Save model history
Author-email: Raffaele Salmaso <raffaele@salmaso.org>
License: Copyright (C) 2017-2022, Raffaele Salmaso <raffaele@salmaso.org>        
Project-URL: Homepage, https://pypi.org/project/django-model-history-log
Project-URL: GitHub, https://github.com/rsalmaso/django-model-history-log
Project-URL: Bug Tracker, https://github.com/rsalmaso/django-model-history-log/issues
Classifier: Development Status :: 5 - Production/Stable
Classifier: Framework :: Django
Classifier: Framework :: Django :: 3.2
Classifier: Framework :: Django :: 4.0
Classifier: Intended Audience :: Developers
Classifier: License :: OSI Approved :: MIT License
Classifier: Natural Language :: English
Classifier: Operating System :: OS Independent
Classifier: Programming Language :: Python
Classifier: Programming Language :: Python :: 3
Classifier: Programming Language :: Python :: 3.8
Classifier: Programming Language :: Python :: 3.9
Classifier: Programming Language :: Python :: 3.10
Requires-Python: >=3.8
License-File: AUTHORS
Requires-Dist: django
Requires-Dist: djangorestframework
